oom_messages_exporter.py
oom_messages_exporter/__init__.py
oom_messages_exporter/cricollector.py
oom_messages_exporter/exporter.py
oom_messages_exporter/filetailer.py
oom_messages_exporter-20230920.dist-info/LICENSE
oom_messages_exporter-20230920.dist-info/METADATA
oom_messages_exporter-20230920.dist-info/WHEEL
oom_messages_exporter-20230920.dist-info/top_level.txt
oom_messages_exporter-20230920.dist-info/RECORD
