Metadata-Version: 2.1
Name: oom-messages-exporter
Version: 20230920
Summary: Collects OOM Killer messages from /var/log/messages and represents the data for Prometheus.
Author-email: Alexey Antropov <alexeyantropov@gmail.com>
Project-URL: Homepage, https://github.com/alexeyantropov/oom_messages_exporter
Project-URL: Bug Tracker, https://github.com/alexeyantropov/oom_messages_exporter/issues
Classifier: Programming Language :: Python :: 3
Classifier: License :: OSI Approved :: MIT License
Classifier: Operating System :: OS Independent
Requires-Python: >=3.7
License-File: LICENSE
Requires-Dist: prometheus-client >=0.17.1
